examples
product_classifier
venv
