Metadata-Version: 2.4
Name: product-classifier
Version: 0.1.0
Summary: CNN+BiLSTM hybrid architecture for product classification
Home-page: https://github.com/turgutguvercin/cnn-bilstm-classifier
Author: Turgut Guvercin
Author-email: Turgut Guvercin <turgut430@gmail.com>
Maintainer-email: Turgut Guvercin <turgut430@gmail.com>
License: MIT
Project-URL: Homepage, https://github.com/turgutguvercin/cnn-bilstm-classifier
Keywords: deep learning,nlp,text classification,cnn,lstm,product classification,pytorch,machine learning
Classifier: Development Status :: 4 - Beta
Classifier: Intended Audience :: Developers
Classifier: Intended Audience :: Science/Research
Classifier: License :: OSI Approved :: MIT License
Classifier: Operating System :: OS Independent
Classifier: Programming Language :: Python :: 3
Classifier: Programming Language :: Python :: 3.8
Classifier: Programming Language :: Python :: 3.9
Classifier: Programming Language :: Python :: 3.10
Classifier: Programming Language :: Python :: 3.11
Classifier: Topic :: Scientific/Engineering :: Artificial Intelligence
Classifier: Topic :: Software Development :: Libraries :: Python Modules
Classifier: Topic :: Text Processing :: Linguistic
Requires-Python: >=3.8
License-File: LICENSE
Requires-Dist: torch>=1.9.0
Requires-Dist: numpy>=1.21.0
Requires-Dist: safetensors>=0.3.0
Requires-Dist: huggingface-hub>=0.15.0
Requires-Dist: gensim>=4.0.0
Requires-Dist: scikit-learn>=1.0.0
Requires-Dist: tqdm>=4.60.0
Provides-Extra: dev
Requires-Dist: pytest>=6.0; extra == "dev"
Requires-Dist: pytest-cov>=2.0; extra == "dev"
Requires-Dist: black>=21.0; extra == "dev"
Requires-Dist: flake8>=3.8; extra == "dev"
Requires-Dist: isort>=5.0; extra == "dev"
Requires-Dist: mypy>=0.900; extra == "dev"
Provides-Extra: docs
Requires-Dist: sphinx>=4.0; extra == "docs"
Requires-Dist: sphinx-rtd-theme>=1.0; extra == "docs"
Requires-Dist: myst-parser>=0.15; extra == "docs"
Provides-Extra: all
Requires-Dist: cnn-bilstm-classifier[dev,docs]; extra == "all"
Dynamic: author
Dynamic: home-page
Dynamic: license-file
Dynamic: requires-python
